{
  "id": "l2",
  "chapterId": "ch_5",
  "title": "Arguments and Parameters 📩",
  "description": "Make your methods flexible by feeding them outside data.",
  "xpReward": 25,
  "estimatedMinutes": 7,
  "section": "Methods",
  "slides": [
    {
      "id": "s_1",
      "type": "text",
      "title": "Flexible Methods 🤸",
      "content": "A method that prints 'Hello World' every time is a bit rigid.\n\nWhat if we want a method that can say hello to *any* name we give it?\n\nWe can do this by using **Parameters** and **Arguments** to pass data into the method."
    },
    {
      "id": "s_2",
      "type": "text",
      "title": "Defining a Parameter",
      "content": "A parameter is a temporary variable that acts like a slot waiting to be filled.\n\nYou place parameters in parentheses `()` right after the method name.\n\n```ruby\ndef greet(name)\n  puts \"Hello there, #{name}!\"\nend\n```"
    },
    {
      "id": "s_3",
      "type": "code",
      "title": "Passing Arguments",
      "content": "When you CALL the method, you pass in the actual data (the \"Argument\"). This real data fills the parameter slot.",
      "codeSnippet": "def greet(name)\n  puts \"Hello there, #{name}!\"\nend\n\ngreet(\"Alice\")\ngreet(\"Bob\")",
      "codeLanguage": "ruby",
      "canRunCode": true
    },
    {
      "id": "s_4",
      "type": "quiz",
      "title": "Quick Check 🧠",
      "content": "What fills the slot?",
      "quizData": {
        "id": "q_1",
        "type": "multiple_choice",
        "question": "In the code `greet(\"Alice\")`, what is \"Alice\"?",
        "options": [
          {
            "id": "opt1",
            "text": "The parameter.",
            "isCorrect": false
          },
          {
            "id": "opt2",
            "text": "The method.",
            "isCorrect": false
          },
          {
            "id": "opt3",
            "text": "The argument.",
            "isCorrect": true
          }
        ],
        "explanation": "The placeholder waiting for data (`name`) is the parameter. The actual 100% real data you feed into it (`\"Alice\"`) is the argument.",
        "xpReward": 10
      }
    },
    {
      "id": "s_5",
      "type": "text",
      "title": "Multiple Parameters 👯",
      "content": "You can define as many parameters as you want by separating them with commas.\n\n```ruby\ndef create_user(first_name, last_name, age)\n  puts \"Welcome #{first_name} #{last_name}! Age: #{age}\"\nend\n```\n\nYou must provide exactly the right amount of arguments when calling it, in the exact same order!"
    },
    {
      "id": "s_6",
      "type": "code",
      "title": "Passing Multiple",
      "content": "Ruby will carefully align the arguments based on the order you passed them.",
      "codeSnippet": "def add_numbers(num1, num2)\n  puts num1 + num2\nend\n\nadd_numbers(10, 5)",
      "codeLanguage": "ruby",
      "canRunCode": true
    },
    {
      "id": "s_7",
      "type": "quiz",
      "title": "Quick Check 🧠",
      "content": "Missing arguments.",
      "quizData": {
        "id": "q_2",
        "type": "multiple_choice",
        "question": "If a method is defined with two parameters, what happens if you try to call it with only one argument?",
        "options": [
          {
            "id": "opt1",
            "text": "Ruby replaces the second parameter with nil.",
            "isCorrect": false
          },
          {
            "id": "opt2",
            "text": "Ruby throws an ArgumentError and crashes.",
            "isCorrect": true
          },
          {
            "id": "opt3",
            "text": "It skips the code requiring the second parameter.",
            "isCorrect": false
          }
        ],
        "explanation": "If a method demands two pieces of data to work, providing only one will trigger an immediate `ArgumentError: wrong number of arguments (given 1, expected 2)`.",
        "xpReward": 10
      }
    }
  ]
}
