{
  "id": "l5",
  "chapterId": "ch_5",
  "title": "Variable Scope 🔭",
  "description": "Learn where variables live and die within your methods.",
  "xpReward": 20,
  "estimatedMinutes": 5,
  "section": "Returns & Scope",
  "slides": [
    {
      "id": "s_1",
      "type": "text",
      "title": "The Fortress 🏰",
      "content": "A crucial rule about methods: they are like self-contained fortresses.\n\nIf you create a variable inside of a method, it is **locked entirely within that method**.\n\nThe outside program has absolutely no idea that variable exists!"
    },
    {
      "id": "s_2",
      "type": "code",
      "title": "Scoping Error",
      "content": "Run this code. It will crash! `secret` only exists inside the walls of the method.",
      "codeSnippet": "def set_password\n  secret = \"password123\"\nend\n\n# Try to grab the variable from the outside\nputs secret",
      "codeLanguage": "ruby",
      "canRunCode": true
    },
    {
      "id": "s_3",
      "type": "quiz",
      "title": "Quick Check 🧠",
      "content": "Where do variables live?",
      "quizData": {
        "id": "q_1",
        "type": "multiple_choice",
        "question": "Can code outside of a method access variables created completely inside the method?",
        "options": [
          {
            "id": "opt1",
            "text": "Yes, standard variables are global.",
            "isCorrect": false
          },
          {
            "id": "opt2",
            "text": "No, variables created inside a method are locked entirely within its scope.",
            "isCorrect": true
          },
          {
            "id": "opt3",
            "text": "Only if you use the 'return' keyword on them.",
            "isCorrect": false
          }
        ],
        "explanation": "This concept is called 'variable scope'. The scope of variables defined within a method does not leak out to the broader script.",
        "xpReward": 10
      }
    },
    {
      "id": "s_4",
      "type": "text",
      "title": "The One-Way Mirror 🪞",
      "content": "Not only can the outside program NOT look in, but the method *cannot look out* either!\n\nA method cannot access standard variables created outside of it.\n\nThe only way to get outside variables inside a method is to explicitly push them through using **Arguments/Parameters**."
    },
    {
      "id": "s_5",
      "type": "code",
      "title": "Passing Scope",
      "content": "Notice how we safely pass the outside variable `money` right through the front gates of the method using the parameter.",
      "codeSnippet": "money = 50\n\ndef check_wealth(cash)\n  puts \"You have #{cash} dollars!\"\nend\n\ncheck_wealth(money)",
      "codeLanguage": "ruby",
      "canRunCode": true
    },
    {
      "id": "s_6",
      "type": "quiz",
      "title": "Quick Check 🧠",
      "content": "Breaking through the mirror.",
      "quizData": {
        "id": "q_2",
        "type": "multiple_choice",
        "question": "What is the primary way to get outside data inside of a walled-off method?",
        "options": [
          {
            "id": "opt1",
            "text": "Using the `return` keyword.",
            "isCorrect": false
          },
          {
            "id": "opt2",
            "text": "Using the `def` keyword.",
            "isCorrect": false
          },
          {
            "id": "opt3",
            "text": "Passing it through explicitly as an Argument into the method's Parameters.",
            "isCorrect": true
          }
        ],
        "explanation": "Arguments are the gateway. When you feed outside data into a parameter, the method can safely use it inside its walls.",
        "xpReward": 10
      }
    }
  ]
}
