{
    "id": "l5",
    "chapterId": "ch_4",
    "title": "Mixins",
    "description": "Reusing code with mixins.",
    "xpReward": 25,
    "estimatedMinutes": 6,
    "section": "Advanced",
    "slides": [
        {
            "id": "s_l5_1",
            "type": "text",
            "title": "What are Mixins? 🧩",
            "content": "# Mixins\n\nMixins are a way to reuse code in multiple class hierarchies.\n\n* A mixin is a class that provides methods to other classes without being a parent.\n* Use the `with` keyword followed by one or more mixin names.\n* Mixins cannot have constructors."
        },
        {
            "id": "s_l5_2",
            "type": "quiz",
            "title": "Quick Check 🧠",
            "content": "",
            "quizData": {
                "id": "q_l5_1",
                "type": "multiple_choice",
                "question": "Which keyword is used to apply mixins?",
                "options": [
                    {
                        "id": "opt1",
                        "text": "extends",
                        "isCorrect": false
                    },
                    {
                        "id": "opt2",
                        "text": "implements",
                        "isCorrect": false
                    },
                    {
                        "id": "opt3",
                        "text": "with",
                        "isCorrect": true
                    },
                    {
                        "id": "opt4",
                        "text": "mixin",
                        "isCorrect": false
                    }
                ],
                "explanation": "`with` is used to include mixins in a class.",
                "xpReward": 10
            }
        },
        {
            "id": "s_l5_3",
            "type": "code",
            "title": "Using a Mixin",
            "content": "Define a `CanFly` mixin and apply it to `Bird` and `Airplane`:",
            "codeSnippet": "mixin CanFly {\n  void fly() {\n    print('Flying...');\n  }\n}\n\nclass Bird with CanFly {}\n\nclass Airplane with CanFly {}\n\nvoid main() {\n  var bird = Bird();\n  bird.fly(); // Flying...\n\n  var plane = Airplane();\n  plane.fly(); // Flying...\n}",
            "codeLanguage": "dart",
            "canRunCode": true
        },
        {
            "id": "s_l5_4",
            "type": "tip",
            "title": "Pro Tip 🚀",
            "content": "## Mixins can have methods and properties\n\nMixins can also define variables, but be cautious about state – mixins are best for behavior."
        }
    ]
}