{
    "id": "l2",
    "chapterId": "ch_6",
    "title": "Creating Data Frames",
    "description": "Create data frames from vectors using data.frame(). Understand row names and column names.",
    "xpReward": 20,
    "estimatedMinutes": 5,
    "section": "Data Frames",
    "slides": [
        {
            "id": "s6_2_1",
            "type": "text",
            "title": "Creating with data.frame() 🛠️",
            "content": "The primary function to create a data frame is `data.frame()`. You provide named vectors (or other objects) as arguments.\n\n```r\ndf <- data.frame(\n  name = c(\"Alice\", \"Bob\", \"Charlie\"),\n  age = c(25, 30, 35),\n  employed = c(TRUE, FALSE, TRUE)\n)\n```\n\nBy default, character vectors are converted to factors (you can change this with `stringsAsFactors = FALSE`)."
        },
        {
            "id": "s6_2_2",
            "type": "code",
            "title": "Create Your First Data Frame",
            "content": "Run this code:",
            "codeSnippet": "df <- data.frame(\n  id = 1:3,\n  name = c(\"Alice\", \"Bob\", \"Charlie\"),\n  score = c(85, 92, 78),\n  stringsAsFactors = FALSE\n)\nprint(df)",
            "codeLanguage": "r",
            "canRunCode": true
        },
        {
            "id": "s6_2_3",
            "type": "quiz",
            "title": "Quick Check 🧠",
            "content": "",
            "quizData": {
                "id": "q6_2_1",
                "type": "multiple_choice",
                "question": "What does `stringsAsFactors = FALSE` do?",
                "options": [
                    {
                        "id": "opt1",
                        "text": "Prevents character columns from being converted to factors",
                        "isCorrect": true
                    },
                    {
                        "id": "opt2",
                        "text": "Converts all columns to factors",
                        "isCorrect": false
                    },
                    {
                        "id": "opt3",
                        "text": "Removes character columns",
                        "isCorrect": false
                    },
                    {
                        "id": "opt4",
                        "text": "It's an error",
                        "isCorrect": false
                    }
                ],
                "explanation": "In older R versions, strings were converted to factors by default. Setting stringsAsFactors=FALSE keeps them as character.",
                "xpReward": 10
            }
        },
        {
            "id": "s6_2_4",
            "type": "text",
            "title": "Row Names",
            "content": "Data frames automatically get row names, usually just `1,2,3,...`. You can assign custom row names with the `row.names` argument or later with `rownames()`.\n\n```r\ndf <- data.frame(\n  x = 1:3, \n  y = 4:6,\n  row.names = c(\"obs1\", \"obs2\", \"obs3\")\n)\n```"
        },
        {
            "id": "s6_2_5",
            "type": "code",
            "title": "Custom Row Names",
            "content": "Try:",
            "codeSnippet": "df <- data.frame(\n  product = c(\"A\", \"B\", \"C\"),\n  price = c(10, 15, 20),\n  row.names = c(\"p1\", \"p2\", \"p3\")\n)\nprint(df)\nrownames(df)",
            "codeLanguage": "r",
            "canRunCode": true
        }
    ]
}