{
    "id": "l1",
    "chapterId": "ch_14",
    "title": "Introduction to Databases and PDO",
    "description": "What is a database? Why use PDO?",
    "xpReward": 20,
    "estimatedMinutes": 6,
    "section": "Basics",
    "slides": [
        {
            "id": "s_l1_1",
            "type": "text",
            "title": "Databases: Organized Data Storage",
            "content": "# What is a Database?\n\nA database is an organized collection of data, typically stored electronically. Most web applications use a **relational database** like MySQL, PostgreSQL, or SQLite. Data is stored in tables (like spreadsheets) with rows and columns.\n\nPHP scripts can connect to a database to store user information, retrieve products, etc."
        },
        {
            "id": "s_l1_2",
            "type": "text",
            "title": "Ways to Connect to MySQL from PHP",
            "content": "# MySQLi vs PDO\n\nPHP offers three main ways to work with MySQL:\n\n1. **mysql** (old, deprecated, don't use)\n2. **MySQLi** (improved, but MySQL-only)\n3. **PDO** (PHP Data Objects) – a database abstraction layer that supports many databases (MySQL, PostgreSQL, SQLite, etc.)\n\nWe'll use **PDO** because it's more flexible, secure, and modern."
        },
        {
            "id": "s_l1_3",
            "type": "text",
            "title": "PDO Advantages",
            "content": "# Why PDO?\n\n*   **Database agnostic** – you can switch database systems with minimal code changes.\n*   **Prepared statements** – built-in protection against SQL injection.\n*   **Object-oriented** – clean, modern interface.\n*   **Named placeholders** – easier to read.\n*   **Exception handling** – works well with try/catch.\n\nPDO is the recommended way to interact with databases in PHP."
        },
        {
            "id": "s_l1_4",
            "type": "quiz",
            "title": "Quick Check 🧠",
            "content": "",
            "quizData": {
                "id": "q_l1_1",
                "type": "multiple_choice",
                "question": "Which PHP extension provides a database abstraction layer that works with multiple databases?",
                "options": [
                    {
                        "id": "opt1",
                        "text": "MySQLi",
                        "isCorrect": false
                    },
                    {
                        "id": "opt2",
                        "text": "PDO",
                        "isCorrect": true
                    },
                    {
                        "id": "opt3",
                        "text": "mysql",
                        "isCorrect": false
                    },
                    {
                        "id": "opt4",
                        "text": "SQLite3",
                        "isCorrect": false
                    }
                ],
                "explanation": "PDO (PHP Data Objects) supports multiple databases, while MySQLi is MySQL-specific.",
                "xpReward": 10
            }
        }
    ]
}