{
    "id": "l1",
    "chapterId": "ch_1",
    "title": "What is React?",
    "description": "Meet React, the library for building user interfaces.",
    "xpReward": 20,
    "estimatedMinutes": 4,
    "section": "Introduction",
    "slides": [
        {
            "id": "s_l1_1",
            "type": "text",
            "title": "React: The UI Library ⚛️",
            "content": "# What is React?\n\nReact is a **JavaScript library** for building interactive user interfaces. Think of it as a box of LEGO® bricks – you assemble small, reusable pieces (components) to create complex applications.\n\n* **Declarative**: You describe *what* you want, and React handles the *how*.\n* **Component‑Based**: Build encapsulated components that manage their own state, then compose them to make rich UIs.\n* **Learn Once, Write Anywhere**: React can also render on the server (Next.js) or power mobile apps (React Native)."
        },
        {
            "id": "s_l1_2",
            "type": "quiz",
            "title": "Quick Check 🧠",
            "content": "",
            "quizData": {
                "id": "q_l1_1",
                "type": "multiple_choice",
                "question": "What is React primarily used for?",
                "options": [
                    {
                        "id": "opt1",
                        "text": "Managing databases",
                        "isCorrect": false
                    },
                    {
                        "id": "opt2",
                        "text": "Building user interfaces",
                        "isCorrect": true
                    },
                    {
                        "id": "opt3",
                        "text": "Styling web pages",
                        "isCorrect": false
                    },
                    {
                        "id": "opt4",
                        "text": "Server‑side logic",
                        "isCorrect": false
                    }
                ],
                "explanation": "React is a library for building user interfaces. It helps you create interactive UIs efficiently.",
                "xpReward": 5
            }
        },
        {
            "id": "s_l1_3",
            "type": "tip",
            "title": "Pro Tip 🚀",
            "content": "## Library vs Framework\n\nReact is a **library**, not a full framework. It focuses on the view layer, so you can combine it with other tools for routing, state management, etc. This gives you flexibility!"
        }
    ]
}