{
  "lessons": [
    {
      "id": "l1",
      "title": "The 'for' Loop",
      "description": "The one and only loop you need in Go.",
      "xpReward": 20,
      "estimatedMinutes": 5,
      "section": "Loops"
    },
    {
      "id": "l2",
      "title": "Go's 'while' Loop",
      "description": "How to write a while loop using 'for'.",
      "xpReward": 20,
      "estimatedMinutes": 5,
      "section": "Loops"
    },
    {
      "id": "l3",
      "title": "Infinite Loops & Break",
      "description": "Loops that run forever, and how to stop them.",
      "xpReward": 20,
      "estimatedMinutes": 5,
      "section": "Control"
    },
    {
      "id": "l4",
      "title": "Skipping with 'continue'",
      "description": "How to skip an iteration safely.",
      "xpReward": 20,
      "estimatedMinutes": 4,
      "section": "Control"
    },
    {
      "id": "l5",
      "title": "Intro to 'range'",
      "description": "The most powerful way to iterate in Go.",
      "xpReward": 20,
      "estimatedMinutes": 6,
      "section": "Advanced Loops"
    }
  ]
}
