{
    "id": "task1",
    "chapterId": "ch_1",
    "title": "Hello Rust",
    "description": "Write a basic Rust program that prints 'Hello Rust!' using the println! macro.",
    "estimatedMinutes": 5,
    "problemStatement": "Welcome to the world of Rust! Your first task is to write a single-line Rust program within the `main` function that prints the string `\"Hello Rust!\"` followed by a newline.\n\n**Requirement:** Use the `println!` macro.",
    "hints": [
        "In Rust, `println!` is a macro, not a function, which is why it ends with an exclamation mark `!`."
    ],
    "expectedOutput": "Hello Rust!",
    "solutionCode": "fn main() {\n    println!(\"Hello Rust!\");\n}"
}
