{
    "id": "task1",
    "chapterId": "ch_6",
    "title": "Define Function",
    "description": "Create a simple function that returns a formatted string.",
    "estimatedMinutes": 5,
    "problemStatement": "Functions bundle logic! Define a function `get_greeting($name)` that returns the string `\"Welcome, $name!\"`. Call it with `\"Progly\"` and print the result.\n\n**Expected Output:** `Welcome, Progly!`.",
    "hints": [
        "Include the `return` keyword to pass the string back to the caller."
    ],
    "expectedOutput": "Welcome, Progly!",
    "solutionCode": "<?php\nfunction get_greeting($name) {\n    return \"Welcome, $name!\";\n}\necho get_greeting(\"Progly\");\n?>"
}
