{
    "id": "l3",
    "chapterId": "ch_2",
    "title": "Numbers: Integers & Floats",
    "description": "Work with whole numbers and decimals in Python.",
    "xpReward": 25,
    "estimatedMinutes": 6,
    "section": "Data Types",
    "slides": [
        {
            "id": "s_l3_1",
            "type": "text",
            "title": "Numbers in Python 🔢",
            "content": "# Two Main Number Types\n\nPython has two main types of numbers:\n\n* **int** (Integer) — Whole numbers\n  * `42`, `-17`, `0`, `1000000`\n* **float** (Floating-point) — Decimal numbers\n  * `3.14`, `-0.5`, `2.0`, `99.99`\n\nPython handles the type automatically!"
        },
        {
            "id": "s_l3_2",
            "type": "quiz",
            "title": "Quick Check 🧠",
            "content": "",
            "quizData": {
                "id": "q_l3_1",
                "type": "multiple_choice",
                "question": "What type is the number 3.14?",
                "options": [
                    {
                        "id": "opt1",
                        "text": "int",
                        "isCorrect": false
                    },
                    {
                        "id": "opt2",
                        "text": "float",
                        "isCorrect": true
                    },
                    {
                        "id": "opt3",
                        "text": "string",
                        "isCorrect": false
                    },
                    {
                        "id": "opt4",
                        "text": "double",
                        "isCorrect": false
                    }
                ],
                "explanation": "3.14 has a decimal point, so it's a float (floating-point number)!",
                "xpReward": 10
            }
        },
        {
            "id": "s_l3_3",
            "type": "code",
            "title": "Integers vs Floats 💻",
            "content": "See both number types in action:",
            "codeSnippet": "# Integers (whole numbers)\nage = 25\nyear = 2024\nnegative = -10\n\n# Floats (decimals)\nprice = 19.99\npi = 3.14159\ntemperature = -5.5\n\nprint(\"Age:\", age, type(age))\nprint(\"Price:\", price, type(price))",
            "codeLanguage": "python",
            "canRunCode": true
        },
        {
            "id": "s_l3_4",
            "type": "text",
            "title": "Basic Math Operations ➕",
            "content": "# Arithmetic in Python\n\n| Operator | Meaning | Example |\n|----------|---------|----------|\n| `+` | Addition | `5 + 3 = 8` |\n| `-` | Subtraction | `5 - 3 = 2` |\n| `*` | Multiplication | `5 * 3 = 15` |\n| `/` | Division | `5 / 3 = 1.67` |\n\nPython can do all basic math!"
        },
        {
            "id": "s_l3_5",
            "type": "code",
            "title": "Math in Action 💻",
            "content": "Try out basic arithmetic:",
            "codeSnippet": "a = 10\nb = 3\n\nprint(\"Addition:\", a + b)\nprint(\"Subtraction:\", a - b)\nprint(\"Multiplication:\", a * b)\nprint(\"Division:\", a / b)",
            "codeLanguage": "python",
            "canRunCode": true
        },
        {
            "id": "s_l3_6",
            "type": "quiz",
            "title": "Math Check 🧠",
            "content": "",
            "quizData": {
                "id": "q_l3_2",
                "type": "multiple_choice",
                "question": "What is 15 / 3 in Python?",
                "options": [
                    {
                        "id": "opt1",
                        "text": "5",
                        "isCorrect": false
                    },
                    {
                        "id": "opt2",
                        "text": "5.0",
                        "isCorrect": true
                    },
                    {
                        "id": "opt3",
                        "text": "4",
                        "isCorrect": false
                    },
                    {
                        "id": "opt4",
                        "text": "Error",
                        "isCorrect": false
                    }
                ],
                "explanation": "Division (/) always returns a float in Python 3! So 15 / 3 = 5.0, not 5.",
                "xpReward": 10
            }
        },
        {
            "id": "s_l3_7",
            "type": "text",
            "title": "Special Division Operators ➗",
            "content": "# Beyond Basic Division\n\n* **`/`** — True division (always float)\n  * `7 / 2 = 3.5`\n* **`//`** — Floor division (integer result)\n  * `7 // 2 = 3`\n* **`%`** — Modulo (remainder)\n  * `7 % 2 = 1`"
        },
        {
            "id": "s_l3_8",
            "type": "code",
            "title": "Division Types 💻",
            "content": "Compare the three division operations:",
            "codeSnippet": "print(\"7 / 2 =\", 7 / 2)   # True division\nprint(\"7 // 2 =\", 7 // 2) # Floor division\nprint(\"7 % 2 =\", 7 % 2)   # Remainder\n\n# Practical: hours and minutes\ntotal_minutes = 135\nhours = total_minutes // 60\nminutes = total_minutes % 60\nprint(f\"{hours} hours and {minutes} minutes\")",
            "codeLanguage": "python",
            "canRunCode": true
        },
        {
            "id": "s_l3_9",
            "type": "quiz",
            "title": "Division Check 🧠",
            "content": "",
            "quizData": {
                "id": "q_l3_3",
                "type": "multiple_choice",
                "question": "What is 17 % 5?",
                "options": [
                    {
                        "id": "opt1",
                        "text": "3",
                        "isCorrect": false
                    },
                    {
                        "id": "opt2",
                        "text": "3.4",
                        "isCorrect": false
                    },
                    {
                        "id": "opt3",
                        "text": "2",
                        "isCorrect": true
                    },
                    {
                        "id": "opt4",
                        "text": "12",
                        "isCorrect": false
                    }
                ],
                "explanation": "17 ÷ 5 = 3 remainder 2. The % operator gives the remainder: 2!",
                "xpReward": 10
            }
        },
        {
            "id": "s_l3_10",
            "type": "text",
            "title": "Exponentiation 📈",
            "content": "# Powers in Python\n\nUse `**` for exponentiation (powers):\n\n```python\n2 ** 3 = 8     # 2 to the power of 3\n10 ** 2 = 100  # 10 squared\n9 ** 0.5 = 3.0 # Square root!\n```\n\nThis works with any numbers, including decimals!"
        },
        {
            "id": "s_l3_11",
            "type": "code",
            "title": "Powers in Action 💻",
            "content": "Calculate powers and roots:",
            "codeSnippet": "print(\"2^3 =\", 2 ** 3)\nprint(\"10^2 =\", 10 **2)\nprint(\"2^10 =\", 2 ** 10)\n\n# Square root (power of 0.5)\nprint(\"√16 =\", 16 ** 0.5)\nprint(\"√2 =\", 2 ** 0.5)",
            "codeLanguage": "python",
            "canRunCode": true
        },
        {
            "id": "s_l3_12",
            "type": "quiz",
            "title": "Power Check 🧠",
            "content": "",
            "quizData": {
                "id": "q_l3_4",
                "type": "multiple_choice",
                "question": "What is 3 ** 4?",
                "options": [
                    {
                        "id": "opt1",
                        "text": "12",
                        "isCorrect": false
                    },
                    {
                        "id": "opt2",
                        "text": "81",
                        "isCorrect": true
                    },
                    {
                        "id": "opt3",
                        "text": "7",
                        "isCorrect": false
                    },
                    {
                        "id": "opt4",
                        "text": "64",
                        "isCorrect": false
                    }
                ],
                "explanation": "3 ** 4 means 3 × 3 × 3 × 3 = 81!",
                "xpReward": 10
            }
        },
        {
            "id": "s_l3_13",
            "type": "text",
            "title": "Order of Operations 📐",
            "content": "# PEMDAS in Python\n\nPython follows math order of operations:\n\n1. **P**arentheses `( )`\n2. **E**xponents `**`\n3. **M**ultiplication & **D**ivision `* / // %`\n4. **A**ddition & **S**ubtraction `+ -`\n\n```python\n2 + 3 * 4 = 14    # Not 20!\n(2 + 3) * 4 = 20  # Parentheses first\n```"
        },
        {
            "id": "s_l3_14",
            "type": "quiz",
            "title": "Order Check 🧠",
            "content": "",
            "quizData": {
                "id": "q_l3_5",
                "type": "multiple_choice",
                "question": "What is 2 + 3 * 4?",
                "options": [
                    {
                        "id": "opt1",
                        "text": "20",
                        "isCorrect": false
                    },
                    {
                        "id": "opt2",
                        "text": "14",
                        "isCorrect": true
                    },
                    {
                        "id": "opt3",
                        "text": "9",
                        "isCorrect": false
                    },
                    {
                        "id": "opt4",
                        "text": "24",
                        "isCorrect": false
                    }
                ],
                "explanation": "Multiplication before addition! 3 * 4 = 12, then 2 + 12 = 14",
                "xpReward": 10
            }
        },
        {
            "id": "s_l3_15",
            "type": "text",
            "title": "Augmented Assignment 📝",
            "content": "# Shortcut Operators\n\nInstead of writing `x = x + 5`, use shortcuts:\n\n| Long form | Shortcut |\n|-----------|----------|\n| `x = x + 5` | `x += 5` |\n| `x = x - 5` | `x -= 5` |\n| `x = x * 5` | `x *= 5` |\n| `x = x / 5` | `x /= 5` |\n\nSaves typing and is cleaner!"
        },
        {
            "id": "s_l3_16",
            "type": "code",
            "title": "Shortcuts in Action 💻",
            "content": "See augmented assignment operators:",
            "codeSnippet": "score = 100\nprint(\"Start:\", score)\n\nscore += 50  # Add 50\nprint(\"After +=50:\", score)\n\nscore -= 30  # Subtract 30\nprint(\"After -=30:\", score)\n\nscore *= 2   # Double it\nprint(\"After *=2:\", score)",
            "codeLanguage": "python",
            "canRunCode": true
        },
        {
            "id": "s_l3_17",
            "type": "quiz",
            "title": "Shortcut Check 🧠",
            "content": "",
            "quizData": {
                "id": "q_l3_6",
                "type": "multiple_choice",
                "question": "If x = 10, what is x after x *= 3?",
                "options": [
                    {
                        "id": "opt1",
                        "text": "13",
                        "isCorrect": false
                    },
                    {
                        "id": "opt2",
                        "text": "30",
                        "isCorrect": true
                    },
                    {
                        "id": "opt3",
                        "text": "7",
                        "isCorrect": false
                    },
                    {
                        "id": "opt4",
                        "text": "3.33",
                        "isCorrect": false
                    }
                ],
                "explanation": "x *= 3 means x = x * 3. So 10 * 3 = 30!",
                "xpReward": 10
            }
        },
        {
            "id": "s_l3_18",
            "type": "text",
            "title": "Useful Math Functions 🔧",
            "content": "# Built-in Number Functions\n\n* `abs(x)` — Absolute value\n* `round(x)` — Round to nearest integer\n* `round(x, n)` — Round to n decimal places\n* `min(a, b, c)` — Smallest value\n* `max(a, b, c)` — Largest value"
        },
        {
            "id": "s_l3_19",
            "type": "code",
            "title": "Math Functions 💻",
            "content": "Try out these useful functions:",
            "codeSnippet": "print(\"abs(-5):\", abs(-5))\nprint(\"round(3.7):\", round(3.7))\nprint(\"round(3.14159, 2):\", round(3.14159, 2))\nprint(\"min(5, 2, 8):\", min(5, 2, 8))\nprint(\"max(5, 2, 8):\", max(5, 2, 8))",
            "codeLanguage": "python",
            "canRunCode": true
        },
        {
            "id": "s_l3_20",
            "type": "tip",
            "title": "Pro Tip 🚀",
            "content": "## The math Module\n\nFor advanced math, import the `math` module:\n\n```python\nimport math\n\nprint(math.pi)        # 3.14159...\nprint(math.sqrt(16))  # 4.0\nprint(math.ceil(3.2)) # 4 (round up)\nprint(math.floor(3.8)) # 3 (round down)\n```\n\nWe'll cover imports later!"
        },
        {
            "id": "s_l3_21",
            "type": "quiz",
            "title": "Final Check 🧠",
            "content": "",
            "quizData": {
                "id": "q_l3_7",
                "type": "multiple_choice",
                "question": "What does round(3.456, 2) return?",
                "options": [
                    {
                        "id": "opt1",
                        "text": "3.4",
                        "isCorrect": false
                    },
                    {
                        "id": "opt2",
                        "text": "3.46",
                        "isCorrect": true
                    },
                    {
                        "id": "opt3",
                        "text": "3.5",
                        "isCorrect": false
                    },
                    {
                        "id": "opt4",
                        "text": "4",
                        "isCorrect": false
                    }
                ],
                "explanation": "round(x, 2) rounds to 2 decimal places. 3.456 rounds to 3.46!",
                "xpReward": 10
            }
        }
    ]
}