{
    "id": "quiz_ch_11",
    "chapterId": "ch_11",
    "title": "Chapter 11 Quiz: Sessions & Cookies",
    "description": "Test your understanding of sessions and cookies!",
    "passingScore": 70,
    "xpReward": 50,
    "questions": [
        {
            "id": "q1",
            "type": "mcq",
            "question": "What is the main reason to use sessions?",
            "options": [
                "To store data permanently",
                "To maintain state across HTTP requests",
                "To speed up the website",
                "To encrypt data"
            ],
            "correctAnswer": 1,
            "explanation": "Sessions allow the server to remember users across requests, overcoming HTTP statelessness."
        },
        {
            "id": "q2",
            "type": "true_false",
            "question": "session_start() must be called before any output.",
            "correctAnswer": true,
            "explanation": "Yes, because it sends a cookie header."
        },
        {
            "id": "q3",
            "type": "mcq",
            "question": "Where is session data stored on the server by default?",
            "options": [
                "In a database",
                "In files (usually in /tmp)",
                "In memory",
                "In cookies"
            ],
            "correctAnswer": 1,
            "explanation": "Default session storage is files in the system's temp directory."
        },
        {
            "id": "q4",
            "type": "mcq",
            "question": "How do you store a value 'user_id' in the session?",
            "options": [
                "$_SESSION['user_id'] = 123;",
                "session_put('user_id', 123);",
                "$session['user_id'] = 123;",
                "set_session('user_id', 123);"
            ],
            "correctAnswer": 0,
            "explanation": "Use the $_SESSION superglobal array."
        },
        {
            "id": "q5",
            "type": "true_false",
            "question": "Cookies are stored on the server.",
            "correctAnswer": false,
            "explanation": "Cookies are stored on the client's browser."
        },
        {
            "id": "q6",
            "type": "mcq",
            "question": "Which function is used to set a cookie?",
            "options": [
                "set_cookie()",
                "cookie_set()",
                "setcookie()",
                "create_cookie()"
            ],
            "correctAnswer": 2,
            "explanation": "setcookie() is the correct function."
        },
        {
            "id": "q7",
            "type": "mcq",
            "question": "What does the 'httponly' flag do?",
            "options": [
                "Makes cookie only sent over HTTPS",
                "Prevents JavaScript from accessing the cookie",
                "Makes cookie expire after session ends",
                "Restricts cookie to a specific path"
            ],
            "correctAnswer": 1,
            "explanation": "httponly prevents access via JavaScript, mitigating XSS."
        },
        {
            "id": "q8",
            "type": "fill_blank",
            "question": "To delete a cookie, set its expiration time to a value in the ______.",
            "options": [
                "future",
                "past",
                "present",
                "zero"
            ],
            "correctAnswer": "past",
            "explanation": "Setting expiration in the past makes the browser discard it."
        },
        {
            "id": "q9",
            "type": "true_false",
            "question": "Session variables are accessible via $_SESSION after session_start().",
            "correctAnswer": true,
            "explanation": "Yes, session_start() populates $_SESSION."
        },
        {
            "id": "q10",
            "type": "mcq",
            "question": "What happens if you don't set an expiration time for a cookie?",
            "options": [
                "It never expires",
                "It becomes a session cookie and expires when the browser closes",
                "It expires after 1 hour",
                "It causes an error"
            ],
            "correctAnswer": 1,
            "explanation": "Without expiration, the cookie is a session cookie."
        },
        {
            "id": "q11",
            "type": "mcq",
            "question": "Which superglobal contains cookie data?",
            "options": [
                "$_GET",
                "$_POST",
                "$_COOKIE",
                "$_SESSION"
            ],
            "correctAnswer": 2,
            "explanation": "$_COOKIE holds cookies sent by the browser."
        },
        {
            "id": "q12",
            "type": "true_false",
            "question": "session_destroy() immediately unsets all session variables.",
            "correctAnswer": false,
            "explanation": "session_destroy() destroys the session data on server, but $_SESSION may still be populated in the current request. You should also clear $_SESSION."
        },
        {
            "id": "q13",
            "type": "mcq",
            "question": "What is the default lifetime of a session?",
            "options": [
                "Until the browser closes",
                "24 minutes (usually set in php.ini)",
                "1 hour",
                "Never"
            ],
            "correctAnswer": 1,
            "explanation": "Session lifetime is configured in php.ini (session.gc_maxlifetime), typically 24 minutes."
        },
        {
            "id": "q14",
            "type": "mcq",
            "question": "Which PHP function regenerates the session ID to prevent session fixation?",
            "options": [
                "session_regenerate_id()",
                "session_id()",
                "session_reset()",
                "session_renew()"
            ],
            "correctAnswer": 0,
            "explanation": "session_regenerate_id() creates a new session ID while preserving data."
        },
        {
            "id": "q15",
            "type": "true_false",
            "question": "Cookies can store up to 4KB of data typically.",
            "correctAnswer": true,
            "explanation": "Yes, most browsers limit cookie size to around 4KB."
        },
        {
            "id": "q16",
            "type": "mcq",
            "question": "How do you unset a single session variable?",
            "options": [
                "unset($_SESSION['var'])",
                "session_unset('var')",
                "$_SESSION['var'] = null",
                "Both A and C"
            ],
            "correctAnswer": 0,
            "explanation": "unset($_SESSION['var']) removes that key. Setting to null leaves the key with null value."
        },
        {
            "id": "q17",
            "type": "mcq",
            "question": "What is a common security risk when using cookies?",
            "options": [
                "Cookie sniffing (if not HTTPS)",
                "Cross-site scripting (XSS) stealing cookies",
                "Cross-site request forgery (CSRF)",
                "All of the above"
            ],
            "correctAnswer": 3,
            "explanation": "All are risks mitigated by secure flags, httponly, and samesite."
        },
        {
            "id": "q18",
            "type": "true_false",
            "question": "The 'samesite' cookie attribute helps prevent CSRF attacks.",
            "correctAnswer": true,
            "explanation": "Yes, it restricts how cookies are sent with cross-site requests."
        },
        {
            "id": "q19",
            "type": "mcq",
            "question": "What does header('Location: page.php') do?",
            "options": [
                "Includes page.php",
                "Redirects the browser to page.php",
                "Outputs the location",
                "Sets a cookie"
            ],
            "correctAnswer": 1,
            "explanation": "It sends a redirect header."
        },
        {
            "id": "q20",
            "type": "mcq",
            "question": "In a login system, why should you use sessions instead of cookies to store logged-in status?",
            "options": [
                "Sessions are faster",
                "Session data is stored on the server, not exposed to client",
                "Cookies cannot store enough data",
                "Sessions are easier to code"
            ],
            "correctAnswer": 1,
            "explanation": "Storing logged-in status in a cookie would allow users to tamper with it; sessions keep data on the server."
        }
    ]
}