{
    "id": "quiz_ch_5",
    "chapterId": "ch_5",
    "title": "Chapter 5 Quiz",
    "description": "Test your knowledge of conditional rendering!",
    "passingScore": 70,
    "xpReward": 50,
    "questions": [
        {
            "id": "q1",
            "type": "mcq",
            "question": "Which of the following cannot be used directly inside JSX curly braces?",
            "options": [
                "Ternary operator",
                "Logical && operator",
                "if statement",
                "Function call"
            ],
            "correctAnswer": 2,
            "explanation": "`if` is a statement, not an expression, so it can't be used inside JSX."
        },
        {
            "id": "q2",
            "type": "true_false",
            "question": "You can use multiple return statements in a component to achieve conditional rendering.",
            "correctAnswer": true,
            "explanation": "Yes, early returns are a common pattern."
        },
        {
            "id": "q3",
            "type": "mcq",
            "question": "What will the following code render if `count` is 0?\n\n```jsx\n<div>{count && <p>Count is positive</p>}</div>\n```",
            "options": [
                "<div><p>Count is positive</p></div>",
                "<div></div>",
                "<div>0</div>",
                "<div>false</div>"
            ],
            "correctAnswer": 2,
            "explanation": "`count` is 0, which is falsy, but React renders the numeric value 0. To avoid this, use `count > 0 && ...`."
        },
        {
            "id": "q4",
            "type": "mcq",
            "question": "How would you conditionally render a login or logout button based on `isLoggedIn`?",
            "options": [
                "{isLoggedIn ? <LogoutButton /> : <LoginButton />}",
                "{if (isLoggedIn) <LogoutButton /> else <LoginButton />}",
                "{isLoggedIn && <LogoutButton />}",
                "{isLoggedIn || <LoginButton />}"
            ],
            "correctAnswer": 0,
            "explanation": "The ternary operator is the correct inline conditional for two branches."
        },
        {
            "id": "q5",
            "type": "true_false",
            "question": "Using an object lookup for conditional rendering is a good pattern when you have many possible values.",
            "correctAnswer": true,
            "explanation": "Yes, it's clean and scalable."
        },
        {
            "id": "q6",
            "type": "mcq",
            "question": "What will the following render if `status` is 'loading'?\n\n```jsx\nconst components = {\n  success: <Success />,\n  error: <Error />\n};\n\nreturn <div>{components[status] || <Loading />}</div>;\n```",
            "options": [
                "<div><Success /></div>",
                "<div><Error /></div>",
                "<div><Loading /></div>",
                "<div></div>"
            ],
            "correctAnswer": 2,
            "explanation": "`components['loading']` is undefined, so the `||` falls back to `<Loading />`."
        },
        {
            "id": "q7",
            "type": "mcq",
            "question": "Which of the following correctly applies a conditional class 'active' when `isActive` is true?",
            "options": [
                "<div class={isActive ? 'active' : ''}>",
                "<div className={isActive ? 'active' : ''}>",
                "<div className={isActive && 'active'}>",
                "Both B and C are valid, but B is safer"
            ],
            "correctAnswer": 3,
            "explanation": "Both B and C work, but B explicitly handles the false case with an empty string, avoiding potential `false` being rendered as a class."
        },
        {
            "id": "q8",
            "type": "fill_blank",
            "question": "The _____ operator is used for inline if/else inside JSX.",
            "options": [
                "ternary",
                "logical AND",
                "logical OR",
                "nullish coalescing"
            ],
            "correctAnswer": "ternary",
            "explanation": "The ternary operator `? :` is used for conditional rendering with two branches."
        },
        {
            "id": "q9",
            "type": "true_false",
            "question": "You can store JSX in a variable and then render it later.",
            "correctAnswer": true,
            "explanation": "Yes, JSX is just an expression, so it can be stored in variables."
        },
        {
            "id": "q10",
            "type": "mcq",
            "question": "What will the following code output if `items` is an empty array?\n\n```jsx\n<div>{items.length > 0 && <p>Items found</p>}</div>\n```",
            "options": [
                "<div><p>Items found</p></div>",
                "<div></div>",
                "<div>false</div>",
                "<div>0</div>"
            ],
            "correctAnswer": 1,
            "explanation": "`items.length > 0` is false, so the && returns false, and React renders nothing for booleans. The `<div>` remains empty."
        },
        {
            "id": "q11",
            "type": "mcq",
            "question": "Which pattern would you use to conditionally render one of three different components based on a `status` string?",
            "options": [
                "Ternary chain: status === 'a' ? <A /> : status === 'b' ? <B /> : <C />",
                "if/else if/else outside JSX",
                "Object lookup",
                "All of the above"
            ],
            "correctAnswer": 3,
            "explanation": "All are possible; choice depends on readability and number of cases."
        },
        {
            "id": "q12",
            "type": "true_false",
            "question": "The logical && operator always returns a boolean.",
            "correctAnswer": false,
            "explanation": "It returns the first falsy value or the last truthy value. For example, `3 && 4` returns `4`."
        },
        {
            "id": "q13",
            "type": "mcq",
            "question": "What is the output of `true && 'hello' && 'world'`?",
            "options": [
                "true",
                "hello",
                "world",
                "false"
            ],
            "correctAnswer": 2,
            "explanation": "It evaluates each operand; all are truthy, so it returns the last value: 'world'."
        },
        {
            "id": "q14",
            "type": "fill_blank",
            "question": "In React, values like `false`, `null`, `undefined`, and `true` are _____ when rendered.",
            "options": [
                "ignored",
                "converted to strings",
                "errors",
                "displayed as text"
            ],
            "correctAnswer": "ignored",
            "explanation": "React ignores these values and renders nothing for them."
        },
        {
            "id": "q15",
            "type": "mcq",
            "question": "Why is it recommended to use `condition && <Component />` instead of `condition ? <Component /> : null`?",
            "options": [
                "It's shorter and more readable",
                "It avoids the ternary operator",
                "Both are equivalent; it's a matter of style",
                "The ternary is slower"
            ],
            "correctAnswer": 2,
            "explanation": "Both work exactly the same; it's a stylistic choice. Some prefer && for simplicity when there's no else branch."
        },
        {
            "id": "q16",
            "type": "true_false",
            "question": "You can use a `switch` statement inside JSX.",
            "correctAnswer": false,
            "explanation": "`switch` is a statement, not an expression, so it cannot be used inside JSX. However, you can use it outside and assign the result to a variable."
        },
        {
            "id": "q17",
            "type": "mcq",
            "question": "What will the following render if `user` is `null`?\n\n```jsx\nfunction Profile({ user }) {\n  if (!user) return null;\n  return <div>{user.name}</div>;\n}\n```",
            "options": [
                "<div></div>",
                "null",
                "Nothing (the component returns null, so nothing is rendered)",
                "An error"
            ],
            "correctAnswer": 2,
            "explanation": "Returning `null` from a component renders nothing, so no output is shown."
        },
        {
            "id": "q18",
            "type": "mcq",
            "question": "Which approach is best for rendering a component only when `show` is true?",
            "options": [
                "{show ? <MyComponent /> : null}",
                "{show && <MyComponent />}",
                "{show ? <MyComponent /> : undefined}",
                "All are valid, but B is most concise"
            ],
            "correctAnswer": 3,
            "explanation": "A, B, and C all work (undefined is also ignored). B is the most concise and commonly used."
        },
        {
            "id": "q19",
            "type": "true_false",
            "question": "Conditional rendering only applies to elements; you cannot conditionally apply attributes.",
            "correctAnswer": false,
            "explanation": "You can conditionally apply attributes, e.g., `disabled={isDisabled}` or `className={isActive ? 'active' : ''}`."
        },
        {
            "id": "q20",
            "type": "fill_blank",
            "question": "When using &&, be careful with _____ values like 0 because they will be rendered.",
            "options": [
                "falsy",
                "truthy",
                "numeric",
                "boolean"
            ],
            "correctAnswer": "falsy",
            "explanation": "Falsy values that are not ignored (0, NaN, '') can appear in the output."
        }
    ]
}