{
    "id": "quiz_ch_7",
    "chapterId": "ch_7",
    "title": "Chapter 7 Quiz",
    "description": "Test your knowledge of forms and controlled components!",
    "passingScore": 70,
    "xpReward": 50,
    "questions": [
        {
            "id": "q1",
            "type": "mcq",
            "question": "What is a controlled component in React?",
            "options": [
                "A component that controls its own state without React",
                "A form element whose value is controlled by React state",
                "A component that cannot be changed",
                "A component that uses refs"
            ],
            "correctAnswer": 1,
            "explanation": "A controlled component's value is set by React state and updated via onChange."
        },
        {
            "id": "q2",
            "type": "true_false",
            "question": "In a controlled input, you must use both `value` and `onChange` props.",
            "correctAnswer": true,
            "explanation": "Yes, `value` sets the displayed value, and `onChange` updates the state."
        },
        {
            "id": "q3",
            "type": "mcq",
            "question": "What happens if you set `value` on an input but don't provide an `onChange` handler?",
            "options": [
                "The input becomes read-only",
                "The input works normally but React warns you",
                "The input throws an error",
                "The input ignores the value"
            ],
            "correctAnswer": 0,
            "explanation": "Without onChange, the input's value cannot be updated by typing, so it becomes effectively read-only. React also warns you."
        },
        {
            "id": "q4",
            "type": "mcq",
            "question": "How do you set the initial value for an uncontrolled input?",
            "options": [
                "value",
                "defaultValue",
                "initialValue",
                "startValue"
            ],
            "correctAnswer": 1,
            "explanation": "`defaultValue` sets the initial value but does not control subsequent changes."
        },
        {
            "id": "q5",
            "type": "true_false",
            "question": "In React, a `<select>` element uses the `selected` attribute on the `<option>` to mark the selected item.",
            "correctAnswer": false,
            "explanation": "No, you set `value` on the `<select>` itself, and React matches it."
        },
        {
            "id": "q6",
            "type": "mcq",
            "question": "Which attribute do you use to read the current value from an uncontrolled input using a ref?",
            "options": [
                "ref.current.value",
                "ref.current.inputValue",
                "ref.value",
                "ref.current.text"
            ],
            "correctAnswer": 0,
            "explanation": "The ref gives you the DOM node, and you access its `value` property."
        },
        {
            "id": "q7",
            "type": "fill_blank",
            "question": "To stop a form from refreshing the page, call `e._____()` in the submit handler.",
            "options": [
                "stopPropagation",
                "preventDefault",
                "cancelBubble",
                "halt"
            ],
            "correctAnswer": "preventDefault",
            "explanation": "`preventDefault()` prevents the default form submission behavior."
        },
        {
            "id": "q8",
            "type": "mcq",
            "question": "What is the correct way to handle multiple inputs with a single state object?",
            "options": [
                "Use a separate useState for each input",
                "Use an object and update with `[e.target.name]: e.target.value`",
                "Use a ref for each input",
                "Use a global variable"
            ],
            "correctAnswer": 1,
            "explanation": "Using a single object and the `name` attribute is efficient and scalable."
        },
        {
            "id": "q9",
            "type": "true_false",
            "question": "Checkboxes in controlled components use the `checked` prop instead of `value`.",
            "correctAnswer": true,
            "explanation": "Yes, because checkboxes represent a boolean state, so `checked` is used."
        },
        {
            "id": "q10",
            "type": "mcq",
            "question": "What will be logged if the user types 'hello' in the following input?\n\n```jsx\nconst [text, setText] = useState('');\n<input value={text} onChange={e => setText(e.target.value.toUpperCase())} />\n```",
            "options": [
                "hello",
                "HELLO",
                "An error",
                "Nothing, the input is read-only"
            ],
            "correctAnswer": 1,
            "explanation": "The onChange handler converts the input to uppercase before updating state, so the displayed value will be uppercase."
        },
        {
            "id": "q11",
            "type": "fill_blank",
            "question": "A form element that does not have its value controlled by React is called an _____ component.",
            "options": [
                "uncontrolled",
                "free",
                "native",
                "stateless"
            ],
            "correctAnswer": "uncontrolled",
            "explanation": "Uncontrolled components keep their state in the DOM."
        },
        {
            "id": "q12",
            "type": "mcq",
            "question": "Which hook is used to create a ref in a functional component?",
            "options": [
                "useRef",
                "createRef",
                "refHook",
                "useReference"
            ],
            "correctAnswer": 0,
            "explanation": "`useRef` creates a mutable ref object."
        },
        {
            "id": "q13",
            "type": "true_false",
            "question": "You can use both `value` and `defaultValue` on the same input.",
            "correctAnswer": false,
            "explanation": "If you use `value`, the input is controlled; `defaultValue` is ignored. They are mutually exclusive patterns."
        },
        {
            "id": "q14",
            "type": "mcq",
            "question": "What is the event type for a change on a checkbox?",
            "options": [
                "onClick",
                "onChange",
                "onCheck",
                "onToggle"
            ],
            "correctAnswer": 1,
            "explanation": "Checkboxes also use `onChange`, and you get the new checked state from `e.target.checked`."
        },
        {
            "id": "q15",
            "type": "mcq",
            "question": "In a generic change handler for multiple inputs, why do we use `...prev` when setting state?",
            "options": [
                "To merge the new value with the old object",
                "To create a new array",
                "To call the previous state function",
                "It's not necessary"
            ],
            "correctAnswer": 0,
            "explanation": "We need to preserve other fields in the object; spreading the previous state ensures we don't lose them."
        },
        {
            "id": "q16",
            "type": "true_false",
            "question": "Textarea in React uses its children to set the value.",
            "correctAnswer": false,
            "explanation": "No, it uses the `value` prop, just like input."
        },
        {
            "id": "q17",
            "type": "mcq",
            "question": "What will the following code render initially?\n\n```jsx\n<input defaultValue=\"Hello\" />\n```",
            "options": [
                "An input with the value 'Hello'",
                "An empty input",
                "An error",
                "An input with the value 'defaultValue'"
            ],
            "correctAnswer": 0,
            "explanation": "`defaultValue` sets the initial value, so the input shows 'Hello'."
        },
        {
            "id": "q18",
            "type": "fill_blank",
            "question": "To disable a submit button when the form is invalid, you can set the _____ attribute.",
            "options": [
                "disabled",
                "readOnly",
                "inactive",
                "blocked"
            ],
            "correctAnswer": "disabled",
            "explanation": "`disabled={true}` makes the button unclickable."
        },
        {
            "id": "q19",
            "type": "mcq",
            "question": "Which of the following is a valid reason to use an uncontrolled component?",
            "options": [
                "You need real-time validation",
                "You want to integrate with a non-React library that manipulates the DOM",
                "You need to control the input value",
                "You want to reset the form easily"
            ],
            "correctAnswer": 1,
            "explanation": "Uncontrolled components are useful when you need to let the DOM handle state, e.g., with third-party libraries."
        },
        {
            "id": "q20",
            "type": "true_false",
            "question": "Form validation can only be done on submit.",
            "correctAnswer": false,
            "explanation": "Validation can be done on change, on blur, or on submit – all are valid patterns."
        }
    ]
}