{
    "id": "task1",
    "chapterId": "ch_1",
    "title": "Hello React",
    "description": "Render a simple 'Hello React' heading to the user interface.",
    "estimatedMinutes": 5,
    "problemStatement": "Welcome to React! Create a functional component `HelloWorld` that returns an `<h1>` tag with the text `\"Hello React World!\"`.\n\n**Requirement:** Export the component correctly.",
    "hints": [
        "In modern React, a functional component is just a capital-letter function that returns JSX."
    ],
    "expectedOutput": "<h1>Hello React World!</h1>",
    "solutionCode": "const HelloWorld = () => {\n  return <h1>Hello React World!</h1>;\n};\nexport default HelloWorld;"
}
