{
  "id": "l2",
  "chapterId": "ch_10",
  "title": "Traits 🏅",
  "description": "Defining shared behavior.",
  "xpReward": 30,
  "estimatedMinutes": 6,
  "section": "Advanced Type System",
  "slides": [
    {
      "id": "s_l2_1",
      "type": "text",
      "title": "What is a Trait? 🏅",
      "content": "A Trait simply tells the Rust compiler about functionality a particular type has and can share with other types.\n\nIf you know Java or C#, you can think of Traits exactly like **Interfaces**."
    },
    {
      "id": "s_l2_2",
      "type": "code",
      "title": "Defining a Trait 📜",
      "content": "You use the `trait` keyword and then list the method signatures (without the actual code block).",
      "codeSnippet": "pub trait Summary {\n    fn summarize(&self) -> String;\n}",
      "codeLanguage": "rust",
      "canRunCode": false
    },
    {
      "id": "s_l2_3",
      "type": "text",
      "title": "Implementing a Trait 🛠️",
      "content": "Once the Trait exists, you can explicitly implement it for a specific Struct using `impl Trait for Type`.\n\n```rust\npub struct Article { pub text: String }\n\nimpl Summary for Article {\n    fn summarize(&self) -> String {\n        format!(\"Read: {}\", self.text)\n    }\n}\n```"
    },
    {
      "id": "s_l2_4",
      "type": "quiz",
      "title": "Quick Check 🧠",
      "content": "",
      "quizData": {
        "id": "q_l2_1",
        "type": "multiple_choice",
        "question": "What is the core purpose of a Trait in Rust?",
        "options": [
          {"id": "opt1", "text": "To define exactly how much memory a struct uses", "isCorrect": false},
          {"id": "opt2", "text": "To strictly define a shared interface of behavior (methods) that multiple different struct types can implement.", "isCorrect": true},
          {"id": "opt3", "text": "To safely bypass memory checks", "isCorrect": false}
        ],
        "explanation": "Traits cleanly ensure multiple structs implement specific functionality securely.",
        "xpReward": 10
      }
    }
  ]
}
