{
    "id": "l3",
    "chapterId": "ch_5",
    "title": "Updating Arrays 🔄",
    "description": "Modify data stored inside your arrays.",
    "xpReward": 25,
    "estimatedMinutes": 6,
    "section": "Data Structures",
    "slides": [
        {
            "id": "s_l3_1",
            "type": "text",
            "title": "Replacing Items 🪄",
            "content": "We know how to get items *out* of an array (`backpack[0]`).\n\nTo update an item, we treat `backpack[0]` exactly like a standard variable, and use the `=` sign to put new data in it!"
        },
        {
            "id": "s_l3_2",
            "type": "code",
            "title": "Swapping Out 🔄",
            "content": "Let's change the first item from a Sword to a Bow.",
            "codeSnippet": "class Main {\n  public static void main(String[] args) {\n    String[] backpack = {\"Sword\", \"Shield\", \"Potion\"};\n    System.out.println(\"Before: \" + backpack[0]);\n    \n    // Throw out the sword, put a Bow in slot 0\n    backpack[0] = \"Bow\";\n    \n    System.out.println(\"After: \" + backpack[0]);\n  }\n}",
            "codeLanguage": "java",
            "canRunCode": true
        },
        {
            "id": "s_l3_3",
            "type": "quiz",
            "title": "Replacement Check 🧠",
            "content": "",
            "quizData": {
                "id": "q_l3_1",
                "type": "code_output",
                "question": "If `int[] nums = {1, 2, 3};` and we run `nums[1] = 99;`, what does the array hold now?",
                "options": [
                    {
                        "id": "opt1",
                        "text": "{99, 2, 3}",
                        "isCorrect": false
                    },
                    {
                        "id": "opt2",
                        "text": "{1, 99, 3}",
                        "isCorrect": true
                    },
                    {
                        "id": "opt3",
                        "text": "{1, 2, 99}",
                        "isCorrect": false
                    }
                ],
                "explanation": "nums[1] points to the SECOND slot (which held 2). It gets replaced with 99.",
                "xpReward": 10
            }
        },
        {
            "id": "s_l3_4",
            "type": "text",
            "title": "Alternative Initialization 🏗️",
            "content": "Sometimes we know we need 5 items, but we don't know what they are yet.\n\nWe can create an array of empty \"slots\" by using the `new` keyword.\n`int[] blankScores = new int[5];`\n\nThis creates 5 empty boxes of type `int`. We can fill them later."
        }
    ]
}