{
  "lessons": [
    {
      "id": "l1",
      "title": "Creating Classes",
      "description": "Object-oriented blueprints.",
      "xpReward": 20,
      "estimatedMinutes": 5,
      "section": "Classes"
    },
    {
      "id": "l2",
      "title": "Properties & Methods",
      "description": "Adding data and behavior to classes.",
      "xpReward": 20,
      "estimatedMinutes": 5,
      "section": "Classes"
    },
    {
      "id": "l3",
      "title": "Access Modifiers",
      "description": "Control who can see your data.",
      "xpReward": 20,
      "estimatedMinutes": 5,
      "section": "Classes"
    },
    {
      "id": "l4",
      "title": "Readonly in Classes",
      "description": "Making locked class properties.",
      "xpReward": 20,
      "estimatedMinutes": 5,
      "section": "Classes"
    },
    {
      "id": "l5",
      "title": "Implementing Interfaces",
      "description": "Forcing classes to follow the rules.",
      "xpReward": 20,
      "estimatedMinutes": 5,
      "section": "Classes"
    }
  ]
}
